bizcard_ai/__init__.py
bizcard_ai/core.py
bizcard_ai-0.1.0.dist-info/LICENSE
bizcard_ai-0.1.0.dist-info/METADATA
bizcard_ai-0.1.0.dist-info/WHEEL
bizcard_ai-0.1.0.dist-info/RECORD
