Metadata-Version: 2.1
Name: bizcard-ai
Version: 0.1.0
Summary: A tool to extract details from business cards and load them into a Python dict.
License: GNU General Public License v3.0
Author: Kyle Spinelli
Author-email: kyle.spinelli@gmail.com
Requires-Python: >=3.10,<4.0
Classifier: License :: Other/Proprietary License
Classifier: Programming Language :: Python :: 3
Classifier: Programming Language :: Python :: 3.10
Classifier: Programming Language :: Python :: 3.11
Classifier: Programming Language :: Python :: 3.12
Classifier: Programming Language :: Python :: 3.13
Requires-Dist: gradio (>=5.9.1,<6.0.0)
Requires-Dist: langchain (>=0.3.14,<0.4.0)
Requires-Dist: langchain-openai (>=0.2.14,<0.3.0)
